{
  "type": "tconstruct:modifier",
  "allow_crystal": true,
  "conditions": [
    {
      "type": "forge:or",
      "values": [
        {
          "type": "tconstruct:config",
          "prop": "force_integration_materials"
        },
        {
          "type": "forge:and",
          "values": [
            {
              "type": "forge:mod_loaded",
              "modid": "eidolon"
            },
            {
              "type": "dreamtinker:mod_compact_config",
              "modid": "eidolon"
            }
          ]
        }
      ]
    }
  ],
  "inputs": [
    {
      "tag": "forge:gems/shadow_gem"
    },
    {
      "amount_needed": 6,
      "tag": "forge:bones"
    },
    {
      "item": "minecraft:skeleton_skull"
    },
    {
      "item": "minecraft:wither_skeleton_skull"
    },
    {
      "amount_needed": 2,
      "item": "eidolon:death_essence"
    }
  ],
  "level": 1,
  "result": "dreamtinker:eidolon_death_bringer",
  "slots": {
    "upgrades": 1
  },
  "tools": {
    "tag": "dreamtinker:tools/scythe"
  }
}