{
  "type": "tconstruct:modifier",
  "allow_crystal": true,
  "conditions": [
    {
      "type": "forge:or",
      "values": [
        {
          "type": "tconstruct:config",
          "prop": "force_integration_materials"
        },
        {
          "type": "forge:and",
          "values": [
            {
              "type": "forge:mod_loaded",
              "modid": "ars_nouveau"
            },
            {
              "type": "esotericism_tinker:mod_compact_config",
              "modid": "ars_nouveau"
            }
          ]
        }
      ]
    }
  ],
  "inputs": [
    {
      "item": "ars_nouveau:earth_essence"
    },
    {
      "item": "ars_nouveau:water_essence"
    },
    {
      "item": "ars_nouveau:air_essence"
    },
    {
      "item": "ars_nouveau:fire_essence"
    }
  ],
  "level": 1,
  "result": "dreamtinker:cosmogony_tetrad",
  "tools": {
    "tag": "tconstruct:modifiable"
  }
}